modelseedpy/__init__.py
modelseedpy/config.cfg
modelseedpy/helpers.py
modelseedpy/biochem/__init__.py
modelseedpy/biochem/hierarchical_ontology.py
modelseedpy/biochem/modelseed_biochem.py
modelseedpy/biochem/modelseed_builder.py
modelseedpy/biochem/modelseed_compound.py
modelseedpy/biochem/modelseed_reaction.py
modelseedpy/biochem/modelseed_to_cobra.py
modelseedpy/biochem/seed_object.py
modelseedpy/biochem/stoich_integration.py
modelseedpy/biochem/transporters.py
modelseedpy/biochem/utils.py
modelseedpy/community/__init__.py
modelseedpy/community/commkineticpkg.py
modelseedpy/community/dfbapkg.py
modelseedpy/community/mscommunity.py
modelseedpy/community/mscompatibility.py
modelseedpy/core/__init__.py
modelseedpy/core/annotationontology.py
modelseedpy/core/biolog.py
modelseedpy/core/exceptions.py
modelseedpy/core/fbahelper.py
modelseedpy/core/gapfillinghelper.py
modelseedpy/core/msatpcorrection.py
modelseedpy/core/msbuilder.py
modelseedpy/core/mseditorapi.py
modelseedpy/core/msgapfill.py
modelseedpy/core/msgenome.py
modelseedpy/core/msgenomeclassifier.py
modelseedpy/core/msgrowthphenotypes.py
modelseedpy/core/msmedia.py
modelseedpy/core/msmodel.py
modelseedpy/core/msmodelreport.py
modelseedpy/core/msmodelutl.py
modelseedpy/core/mstemplate.py
modelseedpy/core/rast_client.py
modelseedpy/core/rpcclient.py
modelseedpy/core/template.py
modelseedpy/data/ModelReportTemplate.html
modelseedpy/data/atp_medias.tsv
modelseedpy/fbapkg/__init__.py
modelseedpy/fbapkg/basefbapkg.py
modelseedpy/fbapkg/bilevelpkg.py
modelseedpy/fbapkg/changeoptpkg.py
modelseedpy/fbapkg/drainfluxpkg.py
modelseedpy/fbapkg/elementuptakepkg.py
modelseedpy/fbapkg/flexiblebiomasspkg.py
modelseedpy/fbapkg/fluxfittingpkg.py
modelseedpy/fbapkg/fullthermopkg.py
modelseedpy/fbapkg/gapfillingpkg.py
modelseedpy/fbapkg/kbasemediapkg.py
modelseedpy/fbapkg/metabofbapkg.py
modelseedpy/fbapkg/mspackagemanager.py
modelseedpy/fbapkg/objconstpkg.py
modelseedpy/fbapkg/problemreplicationpkg.py
modelseedpy-0.4.2.dist-info/LICENSE
modelseedpy-0.4.2.dist-info/METADATA
modelseedpy-0.4.2.dist-info/WHEEL
modelseedpy-0.4.2.dist-info/top_level.txt
modelseedpy-0.4.2.dist-info/RECORD
