Metadata-Version: 2.2
Name: ModelSEEDpy
Version: 0.4.2
Summary: Python package for building and analyzing models using ModelSEED
Home-page: https://github.com/ModelSEED/ModelSEEDpy
Author: Christopher Henry
Author-email: chenry@anl.gov
License: MIT License
Project-URL: Documentation, https://modelseedpy.readthedocs.io/en/latest/
Project-URL: Issues, https://github.com/ModelSEED/ModelSEEDpy/issues
Classifier: Development Status :: 3 - Alpha
Classifier: Topic :: Scientific/Engineering :: Bio-Informatics
Classifier: Intended Audience :: Science/Research
Classifier: Operating System :: OS Independent
Classifier: Programming Language :: Python :: 3.9
Classifier: Programming Language :: Python :: 3.10
Classifier: Programming Language :: Python :: 3.11
Classifier: Natural Language :: English
License-File: LICENSE
Requires-Dist: networkx>=2.4
Requires-Dist: cobra>=0.29.0
Requires-Dist: pandas>=2.2.2
Requires-Dist: scikit-learn>=1.2.0
Requires-Dist: scipy>=1.5.4
Requires-Dist: chemicals>=1.0.13
Requires-Dist: chemw>=0.3.2
Requires-Dist: matplotlib>=3.0.0
Requires-Dist: Jinja2>=3.1.4
Requires-Dist: sympy>=1.12.0
Dynamic: author
Dynamic: author-email
Dynamic: classifier
Dynamic: description
Dynamic: description-content-type
Dynamic: home-page
Dynamic: license
Dynamic: project-url
Dynamic: requires-dist
Dynamic: summary
